gcd/controller.v
module controller(lda,ldb,sel1,sel2,sel_in,done,start,lt,gt,eq,clk);
    input start,lt,gt,eq,clk;
    output reg lda,ldb,sel1,sel2,sel_in,done;
    reg[2:0]state;
    parameter S0=3'b000,S1=3'b001,S2=3'b010,S3=3'b011,S4=3'b100,S5=3'b101;

    always@(posedge clk)begin
        case(state)
            S0:begin
                if(start)begin
                    state<=S1;
                end
            end
            S1:begin
                state<=S2;
            end
            S2:begin
                if(eq)begin
                    state<=S5;
                end
                else if(lt)begin
                    state<=S3;
                end
                else if(gt)begin
                    state<=S4;
                end
            end
            S3:begin
                if(eq)begin
                    state<=S5;
                end
                else if(lt)begin
                    state<=S3;
                end
                else if(gt)begin
                    state<=S4;
                end
            end
            S4:begin
                if(eq)begin
                    state<=S5;
                end
                else if(lt)begin
                    state<=S3;
                end
                else if(gt)begin
                    state<=S4;
                end
            end
            S5:begin
                state<=S0;
            end
            default:begin
                state<=S0;
            end
        endcase
    end

    always@(*)begin
        case(state)
            S0:begin
                lda=1'b1;
                sel_in=1'b0;
                ldb=1'b0;
                done=1'b0;
                sel1=1'b1;   // X = a_out
                sel2=1'b0;   // Y = b_out
            end
            S1:begin
                lda=1'b0;
                sel_in=1'b0;
                ldb=1'b1;
                done=1'b0;
                sel1=1'b1;   // X = a_out
                sel2=1'b0;   // Y = b_out
            end
            S2:begin
                if(eq)begin
                    done=1'b1;
                end
                else if(lt)begin
                    sel_in=1'b1;
                    sel1=1'b0;   // X = b_out (larger)
                    sel2=1'b1;   // Y = a_out (smaller)
                    lda=1'b0;
                    ldb=1'b1;
                end
                else if(gt)begin
                    sel1=1'b1;   // X = a_out (larger)
                    sel2=1'b0;   // Y = b_out (smaller)
                    sel_in=1'b1;
                    lda=1'b1;
                    ldb=1'b0;
                end
            end
            S3:begin
                if(eq)begin
                    done=1'b1;
                end
                else if(lt)begin
                    sel_in=1'b1;
                    sel1=1'b0;
                    sel2=1'b1;
                    lda=1'b0;
                    ldb=1'b1;
                end
                else if(gt)begin
                    sel1=1'b1;
                    sel2=1'b0;
                    sel_in=1'b1;
                    lda=1'b1;
                    ldb=1'b0;
                end
            end
            S4:begin
                if(eq)begin
                    done=1'b1;
                end
                else if(lt)begin
                    sel_in=1'b1;
                    sel1=1'b0;
                    sel2=1'b1;
                    lda=1'b0;
                    ldb=1'b1;
                end
                else if(gt)begin
                    sel1=1'b1;
                    sel2=1'b0;
                    sel_in=1'b1;
                    lda=1'b1;
                    ldb=1'b0;
                end
            end
            S5:begin
                done=1'b1;
                sel1=0;
                sel2=0;
                lda=0;
                ldb=0;
            end
            default:begin
                lda=0;
                ldb=0;
            end
        endcase
    end
endmodule

gcd/sub.v
module sub(z,x,y);
    input [15:0]x,y;
    output reg [15:0]z;
    always@(*)begin
        z=x-y;
    end
    endmodule

gcd/comp.v
module comp(eq,lt,gt,data1,data2);
    input [15:0]data1,data2;
    output eq,lt,gt;
    assign eq = (data1==data2);
    assign lt = (data1<data2);
    assign gt = (data1>data2);
endmodule

gcd/mux.v
module mux(out,in0,in1,sel);
    input [15:0]in0,in1;
    input sel;
    output  [15:0]out;
    assign out = sel ? in0 : in1;
endmodule

gcd/pipo1.v
module pipo1(data_out,bus,ld,clk);
    input clk;
    input ld;
    input [15:0]bus;
    output reg [15:0]data_out;
always@(posedge clk) begin
    if(ld)begin
        data_out<=bus;
    end
end
endmodule

gcd/datapath.v
module datapath(EQ,LT,GT,data_in,LDA,LDB,SEL1,SEL2,SEL_IN,CLK);
    input[15:0]data_in;
    wire [15:0]a_out,b_out;
    wire[15:0]X,Y;
    wire[15:0]Bus,Z;
    input CLK,LDA,LDB,SEL1,SEL2,SEL_IN;
    output EQ,LT,GT;
    

    pipo1 A(a_out,Bus,LDA,CLK);
    pipo1 B(b_out,Bus,LDB,CLK);
    mux MUX1(X,a_out,b_out,SEL1);
    mux MUX2(Y,a_out,b_out,SEL2);
    mux MUX3(Bus,Z,data_in,SEL_IN);
   comp C(EQ,LT,GT,a_out,b_out);   // instead of comp C(EQ,LT,GT,X,Y);
    sub S(Z,X,Y);
endmodule

gcd/gcd_tb.v
module gcd_tb;
    reg[15:0]data_input;
    reg clk,start;
    wire done;
    wire EQ,LT,GT;
wire LDA,LDB,SEL1,SEL2,SEL_IN;


    datapath DP(EQ,LT,GT,data_input,LDA,LDB,SEL1,SEL2,SEL_IN,clk);
    controller C(LDA,LDB,SEL1,SEL2,SEL_IN,done,start,LT,GT,EQ,clk);
    initial begin
        clk=1'b0;
        #3 start=1'b1;
        #1000 $finish;
    end
    always #5 clk=~clk;
    initial begin
        data_input=16'd143;
        #20 data_input=16'd78;
    end
    initial begin
        $monitor("time=%0t\tstate=%b\tlda=%b\tldb=%b\tsel1=%b\tsel2=%b\tsel_in=%b\teq=%b\tlt=%b\tgt=%b\ta_out=%0d\tdone=%b",
          $time, C.state, LDA, LDB, SEL1, SEL2, SEL_IN, EQ, LT, GT, DP.a_out, done);
        $dumpfile("gcd.vcd");
        $dumpvars(0,gcd_tb);
    end
endmodule

gcd/gcd.vcd
$date
	Mon Aug 17 02:32:15 2026
$end
$version
	Icarus Verilog
$end
$timescale
	1s
$end
$scope module gcd_tb $end
$var wire 1 ! done $end
$var wire 1 " SEL_IN $end
$var wire 1 # SEL2 $end
$var wire 1 $ SEL1 $end
$var wire 1 % LT $end
$var wire 1 & LDB $end
$var wire 1 ' LDA $end
$var wire 1 ( GT $end
$var wire 1 ) EQ $end
$var reg 1 * clk $end
$var reg 16 + data_input [15:0] $end
$var reg 1 , start $end
$scope module C $end
$var wire 1 * clk $end
$var wire 1 , start $end
$var wire 1 % lt $end
$var wire 1 ( gt $end
$var wire 1 ) eq $end
$var parameter 3 - S0 $end
$var parameter 3 . S1 $end
$var parameter 3 / S2 $end
$var parameter 3 0 S3 $end
$var parameter 3 1 S4 $end
$var parameter 3 2 S5 $end
$var reg 1 ! done $end
$var reg 1 ' lda $end
$var reg 1 & ldb $end
$var reg 1 $ sel1 $end
$var reg 1 # sel2 $end
$var reg 1 " sel_in $end
$var reg 3 3 state [2:0] $end
$upscope $end
$scope module DP $end
$var wire 1 * CLK $end
$var wire 1 ' LDA $end
$var wire 1 & LDB $end
$var wire 1 $ SEL1 $end
$var wire 1 # SEL2 $end
$var wire 1 " SEL_IN $end
$var wire 16 4 data_in [15:0] $end
$var wire 16 5 b_out [15:0] $end
$var wire 16 6 a_out [15:0] $end
$var wire 16 7 Z [15:0] $end
$var wire 16 8 Y [15:0] $end
$var wire 16 9 X [15:0] $end
$var wire 1 % LT $end
$var wire 1 ( GT $end
$var wire 1 ) EQ $end
$var wire 16 : Bus [15:0] $end
$scope module A $end
$var wire 1 * clk $end
$var wire 1 ' ld $end
$var wire 16 ; bus [15:0] $end
$var reg 16 < data_out [15:0] $end
$upscope $end
$scope module B $end
$var wire 1 * clk $end
$var wire 1 & ld $end
$var wire 16 = bus [15:0] $end
$var reg 16 > data_out [15:0] $end
$upscope $end
$scope module C $end
$var wire 1 % lt $end
$var wire 1 ( gt $end
$var wire 1 ) eq $end
$var wire 16 ? data2 [15:0] $end
$var wire 16 @ data1 [15:0] $end
$upscope $end
$scope module MUX1 $end
$var wire 16 A in0 [15:0] $end
$var wire 16 B in1 [15:0] $end
$var wire 1 $ sel $end
$var wire 16 C out [15:0] $end
$upscope $end
$scope module MUX2 $end
$var wire 16 D in0 [15:0] $end
$var wire 16 E in1 [15:0] $end
$var wire 1 # sel $end
$var wire 16 F out [15:0] $end
$upscope $end
$scope module MUX3 $end
$var wire 16 G in1 [15:0] $end
$var wire 1 " sel $end
$var wire 16 H out [15:0] $end
$var wire 16 I in0 [15:0] $end
$upscope $end
$scope module S $end
$var wire 16 J x [15:0] $end
$var wire 16 K y [15:0] $end
$var reg 16 L z [15:0] $end
$upscope $end
$upscope $end
$upscope $end
$enddefinitions $end
$comment Show the parameter values. $end
$dumpall
b101 2
b100 1
b11 0
b10 /
b1 .
b0 -
$end
#0
$dumpvars
bx L
bx K
bx J
bx I
bx H
b10001111 G
bx F
bx E
bx D
bx C
bx B
bx A
bx @
bx ?
bx >
bx =
bx <
bx ;
bx :
bx 9
bx 8
bx 7
bx 6
bx 5
b10001111 4
bx 3
x,
b10001111 +
0*
x)
x(
x'
x&
x%
x$
x#
x"
x!
$end
#3
1,
#5
b10001111 :
b10001111 ;
b10001111 =
b10001111 H
0#
1$
0!
0&
0"
1'
b0 3
1*
#10
0*
#15
1&
0'
b10001111 9
b10001111 @
b10001111 C
b10001111 J
b1 3
b10001111 6
b10001111 <
b10001111 A
b10001111 D
1*
#20
b1001110 :
b1001110 ;
b1001110 =
b1001110 H
0*
b1001110 +
b1001110 4
b1001110 G
#25
b1000001 7
b1000001 I
b1000001 L
b1000001 :
b1000001 ;
b1000001 =
b1000001 H
b1001110 8
b1001110 F
b1001110 K
0&
1'
1"
0)
0%
1(
b1001110 5
b1001110 >
b1001110 @
b1001110 B
b1001110 E
b10 3
1*
#30
0*
#35
b1101 :
b1101 ;
b1101 =
b1101 H
b1000001 8
b1000001 F
b1000001 K
b1101 7
b1101 I
b1101 L
1&
0'
1#
0$
b1001110 9
b1001110 C
b1001110 J
b100 3
1%
0(
b1000001 6
b1000001 <
b1000001 ?
b1000001 A
b1000001 D
1*
#40
0*
#45
b110100 :
b110100 ;
b110100 =
b110100 H
b110100 7
b110100 I
b110100 L
b1101 8
b1101 F
b1101 K
b1000001 9
b1000001 C
b1000001 J
0&
1'
0#
1$
0%
1(
b1101 5
b1101 >
b1101 @
b1101 B
b1101 E
b11 3
1*
#50
0*
#55
b100111 :
b100111 ;
b100111 =
b100111 H
b100111 7
b100111 I
b100111 L
b110100 9
b110100 C
b110100 J
b100 3
b110100 6
b110100 <
b110100 ?
b110100 A
b110100 D
1*
#60
0*
#65
b11010 :
b11010 ;
b11010 =
b11010 H
b11010 7
b11010 I
b11010 L
b100111 9
b100111 C
b100111 J
b100111 6
b100111 <
b100111 ?
b100111 A
b100111 D
1*
#70
0*
#75
b1101 :
b1101 ;
b1101 =
b1101 H
b1101 7
b1101 I
b1101 L
b11010 9
b11010 C
b11010 J
b11010 6
b11010 <
b11010 ?
b11010 A
b11010 D
1*
#80
0*
#85
b0 :
b0 ;
b0 =
b0 H
b0 7
b0 I
b0 L
1!
b1101 9
b1101 C
b1101 J
1)
0(
b1101 6
b1101 <
b1101 ?
b1101 A
b1101 D
1*
#90
0*
#95
b0 :
b0 ;
b0 =
b0 H
b0 7
b0 I
b0 L
0'
0$
b1101 9
b1101 C
b1101 J
b101 3
0)
1%
b0 6
b0 <
b0 ?
b0 A
b0 D
1*
#100
0*
#105
b1111111111110011 7
b1111111111110011 I
b1111111111110011 L
b0 9
b0 C
b0 J
b1001110 :
b1001110 ;
b1001110 =
b1001110 H
1$
0!
0"
1'
b0 3
1*
#110
0*
#115
b1000001 7
b1000001 I
b1000001 L
1&
0'
b1001110 9
b1001110 C
b1001110 J
b1 3
0%
1(
b1001110 6
b1001110 <
b1001110 ?
b1001110 A
b1001110 D
1*
#120
0*
#125
b0 7
b0 I
b0 L
b1001110 8
b1001110 F
b1001110 K
1!
1)
0(
b1001110 5
b1001110 >
b1001110 @
b1001110 B
b1001110 E
b10 3
1*
#130
0*
#135
0&
0$
b101 3
1*
#140
0*
#145
1$
0!
1'
b0 3
1*
#150
0*
#155
1&
0'
b1 3
1*
#160
0*
#165
1!
b10 3
1*
#170
0*
#175
0&
0$
b101 3
1*
#180
0*
#185
1$
0!
1'
b0 3
1*
#190
0*
#195
1&
0'
b1 3
1*
#200
0*
#205
1!
b10 3
1*
#210
0*
#215
0&
0$
b101 3
1*
#220
0*
#225
1$
0!
1'
b0 3
1*
#230
0*
#235
1&
0'
b1 3
1*
#240
0*
#245
1!
b10 3
1*
#250
0*
#255
0&
0$
b101 3
1*
#260
0*
#265
1$
0!
1'
b0 3
1*
#270
0*
#275
1&
0'
b1 3
1*
#280
0*
#285
1!
b10 3
1*
#290
0*
#295
0&
0$
b101 3
1*
#300
0*
#305
1$
0!
1'
b0 3
1*
#310
0*
#315
1&
0'
b1 3
1*
#320
0*
#325
1!
b10 3
1*
#330
0*
#335
0&
0$
b101 3
1*
#340
0*
#345
1$
0!
1'
b0 3
1*
#350
0*
#355
1&
0'
b1 3
1*
#360
0*
#365
1!
b10 3
1*
#370
0*
#375
0&
0$
b101 3
1*
#380
0*
#385
1$
0!
1'
b0 3
1*
#390
0*
#395
1&
0'
b1 3
1*
#400
0*
#405
1!
b10 3
1*
#410
0*
#415
0&
0$
b101 3
1*
#420
0*
#425
1$
0!
1'
b0 3
1*
#430
0*
#435
1&
0'
b1 3
1*
#440
0*
#445
1!
b10 3
1*
#450
0*
#455
0&
0$
b101 3
1*
#460
0*
#465
1$
0!
1'
b0 3
1*
#470
0*
#475
1&
0'
b1 3
1*
#480
0*
#485
1!
b10 3
1*
#490
0*
#495
0&
0$
b101 3
1*
#500
0*
#505
1$
0!
1'
b0 3
1*
#510
0*
#515
1&
0'
b1 3
1*
#520
0*
#525
1!
b10 3
1*
#530
0*
#535
0&
0$
b101 3
1*
#540
0*
#545
1$
0!
1'
b0 3
1*
#550
0*
#555
1&
0'
b1 3
1*
#560
0*
#565
1!
b10 3
1*
#570
0*
#575
0&
0$
b101 3
1*
#580
0*
#585
1$
0!
1'
b0 3
1*
#590
0*
#595
1&
0'
b1 3
1*
#600
0*
#605
1!
b10 3
1*
#610
0*
#615
0&
0$
b101 3
1*
#620
0*
#625
1$
0!
1'
b0 3
1*
#630
0*
#635
1&
0'
b1 3
1*
#640
0*
#645
1!
b10 3
1*
#650
0*
#655
0&
0$
b101 3
1*
#660
0*
#665
1$
0!
1'
b0 3
1*
#670
0*
#675
1&
0'
b1 3
1*
#680
0*
#685
1!
b10 3
1*
#690
0*
#695
0&
0$
b101 3
1*
#700
0*
#705
1$
0!
1'
b0 3
1*
#710
0*
#715
1&
0'
b1 3
1*
#720
0*
#725
1!
b10 3
1*
#730
0*
#735
0&
0$
b101 3
1*
#740
0*
#745
1$
0!
1'
b0 3
1*
#750
0*
#755
1&
0'
b1 3
1*
#760
0*
#765
1!
b10 3
1*
#770
0*
#775
0&
0$
b101 3
1*
#780
0*
#785
1$
0!
1'
b0 3
1*
#790
0*
#795
1&
0'
b1 3
1*
#800
0*
#805
1!
b10 3
1*
#810
0*
#815
0&
0$
b101 3
1*
#820
0*
#825
1$
0!
1'
b0 3
1*
#830
0*
#835
1&
0'
b1 3
1*
#840
0*
#845
1!
b10 3
1*
#850
0*
#855
0&
0$
b101 3
1*
#860
0*
#865
1$
0!
1'
b0 3
1*
#870
0*
#875
1&
0'
b1 3
1*
#880
0*
#885
1!
b10 3
1*
#890
0*
#895
0&
0$
b101 3
1*
#900
0*
#905
1$
0!
1'
b0 3
1*
#910
0*
#915
1&
0'
b1 3
1*
#920
0*
#925
1!
b10 3
1*
#930
0*
#935
0&
0$
b101 3
1*
#940
0*
#945
1$
0!
1'
b0 3
1*
#950
0*
#955
1&
0'
b1 3
1*
#960
0*
#965
1!
b10 3
1*
#970
0*
#975
0&
0$
b101 3
1*
#980
0*
#985
1$
0!
1'
b0 3
1*
#990
0*
#995
1&
0'
b1 3
1*
