up-down-counter/up_down.v
module up_down(
    input clk,clr,mode,ld,
    input[7:0] d,
    output reg[7:0] count
);
always @(posedge clk)
begin
    if(ld)
        count <= d;
    else if(clr)
        count <= 8'b0;
    else if(mode)
        count <= count + 1;
    else
        count <= count - 1;
end
endmodule

up-down-counter/up_down_tb.v
module up_down_tb;
reg Clk, Clr, Mode, Ld;
reg [7:0] D;
wire [7:0] Count;
up_down uut (.clk(Clk), .clr(Clr), .mode(Mode), .ld(Ld), .d(D), .count(Count));
initial begin
    $dumpfile("up_down.vcd");
    $dumpvars(0, up_down_tb);
    $monitor("Time=%0t, Clk=%b, Clr=%b, Mode=%b, Ld=%b, D=%b, Count=%b", $time, Clk, Clr, Mode, Ld, D, Count);
    Clk=0;
    forever #10 Clk=~Clk;
end
initial 
begin
    #10 Clr=1; Ld=0; Mode=0; D=8'b00000000;
    #10 Clr=0; Ld=1; Mode=0; D=8'b00001010;
    #10 Clr=0; Ld=0; Mode=1; D=8'b00000000;
    #50 Clr=0; Ld=0; Mode=0; D=8'b00000000;
    #50 $finish;
end
endmodule

up-down-counter/up_down.vcd
$date
	Mon Jun 15 21:14:26 2026
$end
$version
	Icarus Verilog
$end
$timescale
	1s
$end
$scope module up_down_tb $end
$var wire 8 ! Count [7:0] $end
$var reg 1 " Clk $end
$var reg 1 # Clr $end
$var reg 8 $ D [7:0] $end
$var reg 1 % Ld $end
$var reg 1 & Mode $end
$scope module uut $end
$var wire 1 " clk $end
$var wire 1 # clr $end
$var wire 8 ' d [7:0] $end
$var wire 1 % ld $end
$var wire 1 & mode $end
$var reg 8 ( count [7:0] $end
$upscope $end
$upscope $end
$enddefinitions $end
$comment Show the parameter values. $end
$dumpall
$end
#0
$dumpvars
bx (
bx '
x&
x%
bx $
x#
0"
bx !
$end
#10
b0 !
b0 (
b0 $
b0 '
0&
0%
1#
1"
#20
b1010 $
b1010 '
1%
0#
0"
#30
b1 !
b1 (
b0 $
b0 '
1&
0%
1"
#40
0"
#50
b10 !
b10 (
1"
#60
0"
#70
b11 !
b11 (
1"
#80
0"
0&
#90
b10 !
b10 (
1"
#100
0"
#110
b1 !
b1 (
1"
#120
0"
#130
b0 !
b0 (
1"
