booth-algorithm/controlpath.v
module controlpath(lda,clra,sfta,ldq,clrq,sftq,ldm,clrff,addsub,clk,start,eqz,q0,qm1,done,ldcnt,decr);
    input q0,qm1;
    input clk,start,eqz;
    output reg lda,clra,sfta,ldq,clrq,sftq,ldm,clrff,addsub,done,ldcnt,decr;
    reg [2:0]state;
    parameter S0=3'b000, S1=3'b001, S2=3'b010, CHECK=3'b011,
              ADD=3'b100, SUB=3'b101, SHIFT=3'b110, DONE=3'b111;

    initial state = S0;

    always@(posedge clk)begin
        case(state)
            S0:    if(start) state<=S1;
            S1:    state<=S2;
            S2:    state<=CHECK;
            CHECK: if(eqz)                     state<=DONE;
                   else if({q0,qm1}==2'b01)     state<=ADD;
                   else if({q0,qm1}==2'b10)     state<=SUB;
                   else                         state<=SHIFT;
            ADD:   state<=SHIFT;
            SUB:   state<=SHIFT;
            SHIFT: state<=CHECK;
            DONE:  state<=DONE;
            default: state<=S0;
        endcase
    end

    always@(*)begin
        lda=0; clra=0; sfta=0; ldq=0; clrq=0; sftq=0;
        ldm=0; clrff=0; addsub=0; done=0; ldcnt=0; decr=0;
        case(state)
            S1:    begin clra=1; clrff=1; ldcnt=1; ldm=1; end
            S2:    begin ldq=1; end
            ADD:   begin addsub=1; lda=1; end
            SUB:   begin addsub=0; lda=1; end
            SHIFT: begin sfta=1; sftq=1; decr=1; end
            DONE:  begin done=1; end
            default: ; // S0 and CHECK output nothing
        endcase
    end
endmodule

booth-algorithm/counter.v
module counter(count,ldcnt,clk,decr);
    input ldcnt,clk,decr;
    output reg [4:0]count;
    
    always@(posedge clk)begin
        if(ldcnt)begin
            count<=5'b10000;
        end
        else if (decr) begin
            count<=count-1;
        end
        
        
    end
endmodule

booth-algorithm/alu.v
module alu(z,addsub,a,m);
    input [15:0]a,m;
    input addsub;
    output reg [15:0]z;
    always@(*)begin
        if(addsub==0)begin   //addsub==0 means subtraction
            z=a-m;
        end
        else begin
            z=a+m;
        end
    end
endmodule

booth-algorithm/piporeg.v
module piporeg(data_out,data_in,ldm,clk);
    input ldm,clk;
    input[15:0]data_in;
    output reg [15:0] data_out;
    always@(posedge clk)begin
        if(ldm)
            data_out<=data_in;
    end
endmodule

booth-algorithm/dff.v
module dff(q,clk,clrff,en,d);
    input clk,clrff,en,d;
    output reg q;
    always@(posedge clk)begin
        if(clrff)
            q<=1'b0;
        else if(en)
            q<=d;
    end
endmodule

booth-algorithm/shiftreg.v
module shiftreg(data_out,data_in,ld,clr,clk,sft,sin);
    input sin;
    input ld,clr,clk;
    input[15:0]data_in;
    input sft;
    output reg [15:0] data_out;

    always@(posedge clk)begin
        if(clr)
            data_out<=16'b0;
        else if(ld)
            data_out<=data_in;
       else if(sft)
            data_out<={sin,data_out[15:1]};
    end
endmodule

booth-algorithm/datapath.v
module datapath(qm1,eqz,count,a,m,q,z,q_in,m_in,lda,ldq,ldm,clra,clrq,clrff,sfta,sftq,addsub,clk,start,ldcnt,decr);
    input [15:0] q_in,m_in;
    input lda,ldq,ldm,clra,clrq,clrff,sfta,sftq,addsub,clk,start,ldcnt,decr;
    output qm1,eqz;
    output wire[15:0]z;
    output wire[4:0]count;
    output wire[15:0]a,m;
    output wire[15:0] q;

    assign eqz=~|count;
    shiftreg A(a,z,lda,clra,clk,sfta,a[15]);
    shiftreg Q(q,q_in,ldq,clrq,clk,sftq,a[0]);
    dff D(qm1,clk,clrff,sftq,q[0]);
    piporeg M(m,m_in,ldm,clk);
    alu AL(z,addsub,a,m);
    counter C(count,ldcnt,clk,decr);
endmodule

booth-algorithm/booth_tb.v
module booth_tb;
    reg clk;
    reg [15:0]q_in,m_in;
    wire [15:0]z;
    reg start;
    wire [4:0]count;
    wire qm1, eqz;
    wire[15:0] a,m,q;
    wire lda, ldq, ldm;
    wire clra, clrq, clrff;
    wire sfta, sftq, addsub;
    wire  q0, done;
    wire decr, ldcnt;
   assign q0 = q[0]; 
datapath DP(qm1,eqz,count,a,m,q,z,q_in,m_in,lda,ldq,ldm,clra,clrq,clrff,sfta,sftq,addsub,clk,start,ldcnt,decr);
controlpath CP(lda,clra,sfta,ldq,clrq,sftq,ldm,clrff,addsub,clk,start,eqz,q0,qm1,done,ldcnt,decr);
initial begin
        clk = 0;
        forever #5 clk = ~clk;
    end
     initial begin
        q_in = 16'd3;
         m_in = 16'd5;
        start=0;

        #10
        start = 1;
     #10 start=0;

        #500;
        $finish;
    end
initial begin
    $dumpfile("booth_tb.vcd");
    $dumpvars(0,booth_tb);
$monitor("T=%0t Q=%h A=%h M=%h Z=%h Count=%h state=%b q0=%b qm1=%b lda=%b addsub=%b sfta=%b sftq=%b done=%b",
$time,q,a,m,z,count,CP.state,q0,qm1,lda,addsub,sfta,sftq,done);
end
endmodule

booth-algorithm/booth_tb.vcd
$date
	Mon Aug 24 23:38:57 2026
$end
$version
	Icarus Verilog
$end
$timescale
	1s
$end
$scope module booth_tb $end
$var wire 16 ! z [15:0] $end
$var wire 1 " sftq $end
$var wire 1 # sfta $end
$var wire 1 $ qm1 $end
$var wire 1 % q0 $end
$var wire 16 & q [15:0] $end
$var wire 16 ' m [15:0] $end
$var wire 1 ( ldq $end
$var wire 1 ) ldm $end
$var wire 1 * ldcnt $end
$var wire 1 + lda $end
$var wire 1 , eqz $end
$var wire 1 - done $end
$var wire 1 . decr $end
$var wire 5 / count [4:0] $end
$var wire 1 0 clrq $end
$var wire 1 1 clrff $end
$var wire 1 2 clra $end
$var wire 1 3 addsub $end
$var wire 16 4 a [15:0] $end
$var reg 1 5 clk $end
$var reg 16 6 m_in [15:0] $end
$var reg 16 7 q_in [15:0] $end
$var reg 1 8 start $end
$scope module CP $end
$var wire 1 5 clk $end
$var wire 1 % q0 $end
$var wire 1 8 start $end
$var wire 1 $ qm1 $end
$var wire 1 , eqz $end
$var parameter 3 9 ADD $end
$var parameter 3 : CHECK $end
$var parameter 3 ; DONE $end
$var parameter 3 < S0 $end
$var parameter 3 = S1 $end
$var parameter 3 > S2 $end
$var parameter 3 ? SHIFT $end
$var parameter 3 @ SUB $end
$var reg 1 3 addsub $end
$var reg 1 2 clra $end
$var reg 1 1 clrff $end
$var reg 1 0 clrq $end
$var reg 1 . decr $end
$var reg 1 - done $end
$var reg 1 + lda $end
$var reg 1 * ldcnt $end
$var reg 1 ) ldm $end
$var reg 1 ( ldq $end
$var reg 1 # sfta $end
$var reg 1 " sftq $end
$var reg 3 A state [2:0] $end
$upscope $end
$scope module DP $end
$var wire 1 3 addsub $end
$var wire 1 5 clk $end
$var wire 1 2 clra $end
$var wire 1 1 clrff $end
$var wire 1 0 clrq $end
$var wire 1 . decr $end
$var wire 1 + lda $end
$var wire 1 * ldcnt $end
$var wire 1 ) ldm $end
$var wire 1 ( ldq $end
$var wire 16 B m_in [15:0] $end
$var wire 16 C q_in [15:0] $end
$var wire 1 # sfta $end
$var wire 1 " sftq $end
$var wire 1 8 start $end
$var wire 16 D z [15:0] $end
$var wire 1 $ qm1 $end
$var wire 16 E q [15:0] $end
$var wire 16 F m [15:0] $end
$var wire 1 , eqz $end
$var wire 5 G count [4:0] $end
$var wire 16 H a [15:0] $end
$scope module A $end
$var wire 1 5 clk $end
$var wire 1 2 clr $end
$var wire 1 + ld $end
$var wire 1 # sft $end
$var wire 1 I sin $end
$var wire 16 J data_in [15:0] $end
$var reg 16 K data_out [15:0] $end
$upscope $end
$scope module AL $end
$var wire 16 L a [15:0] $end
$var wire 1 3 addsub $end
$var wire 16 M m [15:0] $end
$var reg 16 N z [15:0] $end
$upscope $end
$scope module C $end
$var wire 1 5 clk $end
$var wire 1 . decr $end
$var wire 1 * ldcnt $end
$var reg 5 O count [4:0] $end
$upscope $end
$scope module D $end
$var wire 1 5 clk $end
$var wire 1 1 clrff $end
$var wire 1 P d $end
$var wire 1 " en $end
$var reg 1 $ q $end
$upscope $end
$scope module M $end
$var wire 1 5 clk $end
$var wire 16 Q data_in [15:0] $end
$var wire 1 ) ldm $end
$var reg 16 R data_out [15:0] $end
$upscope $end
$scope module Q $end
$var wire 1 5 clk $end
$var wire 1 0 clr $end
$var wire 16 S data_in [15:0] $end
$var wire 1 ( ld $end
$var wire 1 " sft $end
$var wire 1 T sin $end
$var reg 16 U data_out [15:0] $end
$upscope $end
$upscope $end
$upscope $end
$enddefinitions $end
$comment Show the parameter values. $end
$dumpall
b101 @
b110 ?
b10 >
b1 =
b0 <
b111 ;
b11 :
b100 9
$end
#0
$dumpvars
bx U
xT
b11 S
bx R
b101 Q
xP
bx O
bx N
bx M
bx L
bx K
bx J
xI
bx H
bx G
bx F
bx E
bx D
b11 C
b101 B
b0 A
08
b11 7
b101 6
05
bx 4
03
02
01
00
bx /
0.
0-
x,
0+
0*
0)
0(
bx '
bx &
x%
x$
0#
0"
bx !
$end
#5
15
#10
05
18
#15
1)
1*
11
12
b1 A
15
#20
05
08
#25
0T
0I
b1111111111111011 !
b1111111111111011 D
b1111111111111011 J
b1111111111111011 N
1(
0*
01
0)
02
b0 4
b0 H
b0 K
b0 L
0$
b101 '
b101 F
b101 M
b101 R
0,
b10000 /
b10000 G
b10000 O
b10 A
15
#30
05
#35
0(
1P
1%
b11 A
b11 &
b11 E
b11 U
15
#40
05
#45
1+
b101 A
15
#50
05
#55
1.
1"
1#
0+
b1111111111110110 !
b1111111111110110 D
b1111111111110110 J
b1111111111110110 N
1T
1I
b110 A
b1111111111111011 4
b1111111111111011 H
b1111111111111011 K
b1111111111111011 L
15
#60
05
#65
b1111111111111000 !
b1111111111111000 D
b1111111111111000 J
b1111111111111000 N
0.
0"
0#
b1111111111111101 4
b1111111111111101 H
b1111111111111101 K
b1111111111111101 L
b1000000000000001 &
b1000000000000001 E
b1000000000000001 U
1$
b1111 /
b1111 G
b1111 O
b11 A
15
#70
05
#75
1.
1"
1#
b110 A
15
#80
05
#85
b1111111111111001 !
b1111111111111001 D
b1111111111111001 J
b1111111111111001 N
0T
0P
0%
0.
0"
0#
b1111111111111110 4
b1111111111111110 H
b1111111111111110 K
b1111111111111110 L
b1100000000000000 &
b1100000000000000 E
b1100000000000000 U
b1110 /
b1110 G
b1110 O
b11 A
15
#90
05
#95
b11 !
b11 D
b11 J
b11 N
1+
13
b100 A
15
#100
05
#105
b1111111111111110 !
b1111111111111110 D
b1111111111111110 J
b1111111111111110 N
1T
0I
1.
1"
1#
03
0+
b11 4
b11 H
b11 K
b11 L
b110 A
15
#110
05
#115
0.
0"
0#
b1111111111111100 !
b1111111111111100 D
b1111111111111100 J
b1111111111111100 N
b11 A
b1101 /
b1101 G
b1101 O
0$
b1110000000000000 &
b1110000000000000 E
b1110000000000000 U
b1 4
b1 H
b1 K
b1 L
15
#120
05
#125
1.
1"
1#
b110 A
15
#130
05
#135
0.
0"
0#
b1111111111111011 !
b1111111111111011 D
b1111111111111011 J
b1111111111111011 N
0T
b11 A
b1100 /
b1100 G
b1100 O
b1111000000000000 &
b1111000000000000 E
b1111000000000000 U
b0 4
b0 H
b0 K
b0 L
15
#140
05
#145
1.
1"
1#
b110 A
15
#150
05
#155
0.
0"
0#
b11 A
b1011 /
b1011 G
b1011 O
b111100000000000 &
b111100000000000 E
b111100000000000 U
15
#160
05
#165
1.
1"
1#
b110 A
15
#170
05
#175
0.
0"
0#
b11 A
b1010 /
b1010 G
b1010 O
b11110000000000 &
b11110000000000 E
b11110000000000 U
15
#180
05
#185
1.
1"
1#
b110 A
15
#190
05
#195
0.
0"
0#
b11 A
b1001 /
b1001 G
b1001 O
b1111000000000 &
b1111000000000 E
b1111000000000 U
15
#200
05
#205
1.
1"
1#
b110 A
15
#210
05
#215
0.
0"
0#
b11 A
b1000 /
b1000 G
b1000 O
b111100000000 &
b111100000000 E
b111100000000 U
15
#220
05
#225
1.
1"
1#
b110 A
15
#230
05
#235
0.
0"
0#
b11 A
b111 /
b111 G
b111 O
b11110000000 &
b11110000000 E
b11110000000 U
15
#240
05
#245
1.
1"
1#
b110 A
15
#250
05
#255
0.
0"
0#
b11 A
b110 /
b110 G
b110 O
b1111000000 &
b1111000000 E
b1111000000 U
15
#260
05
#265
1.
1"
1#
b110 A
15
#270
05
#275
0.
0"
0#
b11 A
b101 /
b101 G
b101 O
b111100000 &
b111100000 E
b111100000 U
15
#280
05
#285
1.
1"
1#
b110 A
15
#290
05
#295
0.
0"
0#
b11 A
b100 /
b100 G
b100 O
b11110000 &
b11110000 E
b11110000 U
15
#300
05
#305
1.
1"
1#
b110 A
15
#310
05
#315
0.
0"
0#
b11 A
b11 /
b11 G
b11 O
b1111000 &
b1111000 E
b1111000 U
15
#320
05
#325
1.
1"
1#
b110 A
15
#330
05
#335
0.
0"
0#
b11 A
b10 /
b10 G
b10 O
b111100 &
b111100 E
b111100 U
15
#340
05
#345
1.
1"
1#
b110 A
15
#350
05
#355
0.
0"
0#
b11 A
b1 /
b1 G
b1 O
b11110 &
b11110 E
b11110 U
15
#360
05
#365
1.
1"
1#
b110 A
15
#370
05
#375
0.
0"
0#
1P
1%
b11 A
1,
b0 /
b0 G
b0 O
b1111 &
b1111 E
b1111 U
15
#380
05
#385
1-
b111 A
15
