parity_generator/paritygen.v
module paritygen(
    input x,clk,
    output reg p
);
reg even_odd;
parameter EVEN=1'b0, ODD=1'b1;
always @(posedge clk) 
begin
    case(even_odd)
        EVEN:begin
            p<=x?1:0;
            even_odd<=x?ODD:EVEN; 
    end  
        ODD:begin
            p<=x?0:1;
            even_odd<=x?EVEN:ODD;
        end
        default:begin
            p<=1'b0;
            even_odd<=EVEN;
        end
    endcase
end
endmodule

parity_generator/paritygen_tb.v
module paritygen_tb;
    reg X,CLK;
    wire OUTPUT;

paritygen uut (
        .x(X),
        .clk(CLK),
        .p(OUTPUT)
    );
    initial begin
        $dumpfile("paritygen.vcd");
        $dumpvars(0, paritygen_tb);
        $monitor("Time=%0t,X=%b, CLK=%b, OUTPUT=%b", $time, X, CLK, OUTPUT);
        CLK=1'b0;
    end
        always #5 CLK = ~CLK;
        initial begin
        X=1'b0;
        #2 X=1'b1;
        #10 X=1'b0;
        #10 X=1'b1;
        #10 X=1'b0;
        #10 X=1'b1;
        #10 X=1'b0;
        #10 X=1'b1;
        #10 X=1'b0;
        #10 $finish;
        end
endmodule

parity_generator/paritygen.vcd
$date
	Fri Aug 07 20:45:15 2026
$end
$version
	Icarus Verilog
$end
$timescale
	1s
$end
$scope module paritygen_tb $end
$var wire 1 ! OUTPUT $end
$var reg 1 " CLK $end
$var reg 1 # X $end
$scope module uut $end
$var wire 1 " clk $end
$var wire 1 # x $end
$var parameter 1 $ EVEN $end
$var parameter 1 % ODD $end
$var reg 1 & even_odd $end
$var reg 1 ! p $end
$upscope $end
$upscope $end
$enddefinitions $end
$comment Show the parameter values. $end
$dumpall
1%
0$
$end
#0
$dumpvars
x&
0#
0"
x!
$end
#2
1#
#5
0&
0!
1"
#10
0"
#12
0#
#15
1"
#20
0"
#22
1#
#25
1&
1!
1"
#30
0"
#32
0#
#35
1"
#40
0"
#42
1#
#45
0&
0!
1"
#50
0"
#52
0#
#55
1"
#60
0"
#62
1#
#65
1&
1!
1"
#70
0"
#72
0#
