ring-counter/rc.v
module rc(
    input clk,init,
    output reg[3:0]count
);
always@(posedge clk)
begin
    if(init)
    count<=4'b1000;
    else begin
        count <= count<<1;
        count[0]<= count[3];
  
end
end
endmodule

ring-counter/rc_tb.v
module rc_tb;
reg CLK,INIT;
wire [3:0]COUNT;
rc UUT(
    .clk(CLK),
    .init(INIT),
    .count(COUNT)
);
initial begin
    $dumpfile("rc.vcd");
    $dumpvars(0,rc_tb);
    $monitor("Time =%0t CLK=%b,INIT=%d,COUNT=%d",$time,CLK,INIT,COUNT);
    CLK=0;
    forever #5 CLK=~CLK;
end
initial begin
     #5 INIT=0;
     #10 INIT=1;
     #10 INIT=0;
     #10 INIT=0;
     #100;
     #10 $finish;
  
end
endmodule

ring-counter/rc.vcd
$date
	Tue Jun 23 00:58:59 2026
$end
$version
	Icarus Verilog
$end
$timescale
	1s
$end
$scope module rc_tb $end
$var wire 4 ! COUNT [3:0] $end
$var reg 1 " CLK $end
$var reg 1 # INIT $end
$scope module UUT $end
$var wire 1 " clk $end
$var wire 1 # init $end
$var reg 4 $ count [3:0] $end
$upscope $end
$upscope $end
$enddefinitions $end
$comment Show the parameter values. $end
$dumpall
$end
#0
$dumpvars
bx $
x#
0"
bx !
$end
#5
bx !
bx $
0#
1"
#10
0"
#15
b1000 !
b1000 $
1"
1#
#20
0"
#25
b1 !
b1 $
1"
0#
#30
0"
#35
b10 !
b10 $
1"
#40
0"
#45
b100 !
b100 $
1"
#50
0"
#55
b1000 !
b1000 $
1"
#60
0"
#65
b1 !
b1 $
1"
#70
0"
#75
b10 !
b10 $
1"
#80
0"
#85
b100 !
b100 $
1"
#90
0"
#95
b1000 !
b1000 $
1"
#100
0"
#105
b1 !
b1 $
1"
#110
0"
#115
b10 !
b10 $
1"
#120
0"
#125
b100 !
b100 $
1"
#130
0"
#135
b1000 !
b1000 $
1"
#140
0"
#145
b1 !
b1 $
1"
